alibabacloud_tablestore20201209/__init__.py
alibabacloud_tablestore20201209/client.py
alibabacloud_tablestore20201209/models/__init__.py
alibabacloud_tablestore20201209/models/_bind_instance_2vpc_request.py
alibabacloud_tablestore20201209/models/_bind_instance_2vpc_response.py
alibabacloud_tablestore20201209/models/_bind_instance_2vpc_response_body.py
alibabacloud_tablestore20201209/models/_change_resource_group_request.py
alibabacloud_tablestore20201209/models/_change_resource_group_response.py
alibabacloud_tablestore20201209/models/_change_resource_group_response_body.py
alibabacloud_tablestore20201209/models/_check_instance_policy_request.py
alibabacloud_tablestore20201209/models/_check_instance_policy_response.py
alibabacloud_tablestore20201209/models/_check_instance_policy_response_body.py
alibabacloud_tablestore20201209/models/_create_instance_request.py
alibabacloud_tablestore20201209/models/_create_instance_response.py
alibabacloud_tablestore20201209/models/_create_instance_response_body.py
alibabacloud_tablestore20201209/models/_create_vcuinstance_request.py
alibabacloud_tablestore20201209/models/_create_vcuinstance_response.py
alibabacloud_tablestore20201209/models/_create_vcuinstance_response_body.py
alibabacloud_tablestore20201209/models/_delete_instance_policy_request.py
alibabacloud_tablestore20201209/models/_delete_instance_policy_response.py
alibabacloud_tablestore20201209/models/_delete_instance_policy_response_body.py
alibabacloud_tablestore20201209/models/_delete_instance_request.py
alibabacloud_tablestore20201209/models/_delete_instance_response.py
alibabacloud_tablestore20201209/models/_delete_instance_response_body.py
alibabacloud_tablestore20201209/models/_delete_vcuinstance_request.py
alibabacloud_tablestore20201209/models/_delete_vcuinstance_response.py
alibabacloud_tablestore20201209/models/_delete_vcuinstance_response_body.py
alibabacloud_tablestore20201209/models/_describe_regions_request.py
alibabacloud_tablestore20201209-3.0.0.dist-info/LICENSE
alibabacloud_tablestore20201209-3.0.0.dist-info/METADATA
alibabacloud_tablestore20201209-3.0.0.dist-info/WHEEL
alibabacloud_tablestore20201209-3.0.0.dist-info/top_level.txt
alibabacloud_tablestore20201209-3.0.0.dist-info/RECORD
